Metadata-Version: 2.1
Name: diff-trigger
Version: 1.1.0
Summary: decorator for monitor function result, run callback when result has been changed
Home-page: https://github.com/thuhak/diff_trigger
Author: thuhak
Author-email: thuhak.zhou@nio.com
License: UNKNOWN
Keywords: decorator
Platform: UNKNOWN
